chat_with_pdf/__init__.py
chat_with_pdf/chat_engine.py
chat_with_pdf/embedder.py
chat_with_pdf/integrations/gpts/__init__.py
chat_with_pdf/integrations/gpts/base.py
chat_with_pdf/integrations/gpts/deepseek.py
chat_with_pdf/integrations/gpts/openai.py
chat_with_pdf/integrations/gpts/perplexity.py
chat_with_pdf/pdf_parser.py
chat_with_pdf/retriever.py
chat_with_pdf/settings.py
chat_with_pdf/setup.py
chat_with_pdf/utils.py
chat_with_pdf-0.4.1.dist-info/LICENSE
chat_with_pdf-0.4.1.dist-info/METADATA
chat_with_pdf-0.4.1.dist-info/WHEEL
chat_with_pdf-0.4.1.dist-info/RECORD
