Metadata-Version: 2.1
Name: chat-with-pdf
Version: 0.4.1
Summary: Chat with your PDFs using local embedding search and OpenAI.
Home-page: https://github.com/anandrnair547/chat-with-pdf
License: MIT
Author: Anand R Nair
Author-email: anand547@outlook.com
Requires-Python: >=3.10
Classifier: License :: OSI Approved :: MIT License
Classifier: Programming Language :: Python :: 3
Classifier: Programming Language :: Python :: 3.10
Classifier: Programming Language :: Python :: 3.11
Classifier: Programming Language :: Python :: 3.12
Classifier: Programming Language :: Python :: 3.13
Requires-Dist: numpy (>=1.26.0,<2.0.0)
Requires-Dist: openai (>=1.0.0,<2.0.0)
Requires-Dist: pymupdf (>=1.23.7,<2.0.0)
Requires-Dist: python-dotenv (>=1.1.0,<2.0.0)
Requires-Dist: requests (>=2.32.3,<3.0.0)
Requires-Dist: scikit-learn (>=1.3.0,<2.0.0)
Requires-Dist: sentence-transformers (>=2.2.2,<3.0.0)
Requires-Dist: torch (>=2.2.0,<2.3.0)
Project-URL: Repository, https://github.com/anandrnair547/chat-with-pdf
